README.rst
setup.py
xavier/__init__.py
xavier/active.py
xavier/brain.py
xavier/datastructures.py
xavier/http.py
xavier/taskqueue.py
xavier.egg-info/PKG-INFO
xavier.egg-info/SOURCES.txt
xavier.egg-info/dependency_links.txt
xavier.egg-info/not-zip-safe
xavier.egg-info/requires.txt
xavier.egg-info/top_level.txt
xavier/aws/__init__.py
xavier/aws/func.py
xavier/aws/sns.py
xavier/sentry/__init__.py
xavier/sentry/reporter.py
xavier/slack/__init__.py
xavier/slack/slash.py