Metadata-Version: 1.0
Name: xavier
Version: 0.0.12
Summary: Lambda bot
Home-page: https://github.com/bepress/xavier
Author: Alex Kessinger
Author-email: akessinger@bepress.com
License: MIT
Platform: UNKNOWN
